{
	"Name": "BiFeO3",
	"Comment": "",
	"Reference": "Zhang Yang",
	"P0": "1.0",
	"Landau": {
		 "a1": "1.093*(tem-815.)*1.e5*4",
                "a11": "5.3181089*1.e8*4",
                "a12": "-5.1235375e8*4",
                "a111": "-4.4e8*4",
                "a112": "4*2.0745345393399e8",
                "a123": "4*4.198595543e8",
                "a1111": "4*0.98e8",
                "a1112": "4*1.1e7",
                "a1122": "-9.5e7*4",
                "a1123": "4*2.0e8"

	},
	"Electrostrictive": {
		"Q11": "0.071",
                "Q12": "-0.03",
                "Q44": "0.02015"
	},
	"ElasticStiffness": {
		"C11": "2.28e11",
                "C12": "1.28e11",
                "C44": "6.5e10"
	}
}
